<?xml version="1.0" encoding="utf-8" standalone="yes"?>
<set name="Kings of the Isles" id="22f0dd6c-0b07-42e2-9cdc-c7262929120b" gameId="30c200c9-6c98-49a4-a293-106c06295c05" version="1.0.0.0" gameVersion="1.0.0.0">
  <cards>
    <card name="Balon Greyjoy" id="b4322df8-dc7d-4b22-a28c-2a2e99d3fe74">
      <property name="Type" value="Character" />
      <property name="Faction" value="House Greyjoy" />
      <property name="Text">Pillage. Renown.
<b>Action:</b> Kneel your faction card to choose a card in an opponent's discard pile and put it into play under your control. At the end of the phase, if that card is still in play, shuffle it into its owner's deck.
<i>Errata from FAQ v2.0</i></property>
      <property name="Traits" value="Ironborn. Lord." />
      <property name="Unique" value="Yes" />
      <property name="Loyal" value="Yes" />
      <property name="Cost" value="7" />
      <property name="Strength" value="5" />
      <property name="Deck Limit" value="3" />
      <property name="Illustrator" value="Michele Frigo" />
      <property name="Card Number" value="1" />
      <property name="Icons">
        <s value="military">[Military]</s>
        <s value="power">[Power]</s>
      </property>
    </card>
    <card name="Euron Crow's Eye" id="13e4c927-7611-4e79-aff4-684bfbe5082e">
      <property name="Type" value="Character" />
      <property name="Faction" value="House Greyjoy" />
      <property name="Text">Intimidate.
<b>Reaction:</b> After you marshal Euron Crow's Eye, search your hand, deck, and discard pile for Silence and put it into play. Shuffle your deck.</property>
      <property name="Traits" value="Captain. Ironborn. Lord. Raider." />
      <property name="Unique" value="Yes" />
      <property name="Loyal" value="Yes" />
      <property name="Cost" value="6" />
      <property name="Strength" value="4" />
      <property name="Deck Limit" value="3" />
      <property name="Illustrator" value="Allen Douglas" />
      <property name="Card Number" value="2" />
      <property name="Icons">
        <s value="military">[Military]</s>
        <s value="intrigue">[Intrigue]</s>
        <s value="power">[Power]</s>
      </property>
    </card>
    <card name="Asha Greyjoy" id="fe32b899-10e6-4cdf-9d9d-6b86789cf3b2">
      <property name="Type" value="Character" />
      <property name="Faction" value="House Greyjoy" />
      <property name="Text">Pillage. Stealth.
Each other unique <i>Ironborn</i> character you control gains stealth.</property>
      <property name="Traits" value="Captain. Ironborn. Lady." />
      <property name="Unique" value="Yes" />
      <property name="Loyal" value="No" />
      <property name="Cost" value="6" />
      <property name="Strength" value="5" />
      <property name="Deck Limit" value="3" />
      <property name="Illustrator" value="Josu Hernaiz" />
      <property name="Card Number" value="3" />
      <property name="Icons">
        <s value="military">[Military]</s>
        <s value="power">[Power]</s>
      </property>
    </card>
    <card name="The Knight" id="c4702409-7b4e-4d60-a320-ca8840e131dd">
      <property name="Type" value="Character" />
      <property name="Faction" value="House Greyjoy" />
      <property name="Text">No attachments except <i>Weapon</i>.
While The Knight is attacking alone, he gains stealth and renown.</property>
      <property name="Traits" value="House Harlaw. Knight." />
      <property name="Unique" value="Yes" />
      <property name="Loyal" value="No" />
      <property name="Cost" value="5" />
      <property name="Strength" value="5" />
      <property name="Deck Limit" value="3" />
      <property name="Illustrator" value="Paolo Puggioni" />
      <property name="Card Number" value="4" />
      <property name="Icons">
        <s value="military">[Military]</s>
        <s value="power">[Power]</s>
      </property>
    </card>
    <card name="Aeron Damphair" id="0f729c19-503c-49ed-bffc-0d01dc72c831">
      <property name="Type" value="Character" />
      <property name="Faction" value="House Greyjoy" />
      <property name="Text">Insight.
<b>Reaction:</b> After another <i>Drowned God</i> character you control is killed, draw 1 card. (Limit once per phase.)</property>
      <property name="Traits" value="Drowned God. Ironborn. Lord." />
      <property name="Unique" value="Yes" />
      <property name="Loyal" value="Yes" />
      <property name="Cost" value="5" />
      <property name="Strength" value="3" />
      <property name="Deck Limit" value="3" />
      <property name="Illustrator" value="Josu Hernaiz" />
      <property name="Card Number" value="5" />
      <property name="Icons">
        <s value="intrigue">[Intrigue]</s>
        <s value="power">[Power]</s>
      </property>
    </card>
    <card name="The Drumm" id="d06fb1d1-470f-48c3-a7c1-04bab74a618d">
      <property name="Type" value="Character" />
      <property name="Faction" value="House Greyjoy" />
      <property name="Text">While The Drumm is attacking in a <s value="military">[Military]</s> or <s value="power">[Power]</s> challenge, each character with an <s value="intrigue">[Intrigue]</s> icon cannot be declared as a defender.</property>
      <property name="Traits" value="Captain. Lord." />
      <property name="Unique" value="Yes" />
      <property name="Loyal" value="No" />
      <property name="Cost" value="5" />
      <property name="Strength" value="4" />
      <property name="Deck Limit" value="3" />
      <property name="Illustrator" value="Jeff Lee Johnson" />
      <property name="Card Number" value="6" />
      <property name="Icons">
        <s value="military">[Military]</s>
        <s value="power">[Power]</s>
      </property>
    </card>
    <card name="Gwynesse Harlaw" id="9ad629ce-5d3c-4c58-9c90-d39b69d37252">
      <property name="Type" value="Character" />
      <property name="Faction" value="House Greyjoy" />
      <property name="Text">
        <b>Action:</b> Choose 3 cards in an opponent's discard pile and place them on the bottom of his or her deck in any order. Then, gain 1 gold and draw 1 card. (Limit once per round.)</property>
      <property name="Traits" value="House Harlaw. Lady." />
      <property name="Unique" value="Yes" />
      <property name="Loyal" value="Yes" />
      <property name="Cost" value="4" />
      <property name="Strength" value="3" />
      <property name="Deck Limit" value="3" />
      <property name="Illustrator" value="Drazenka Kimpel" />
      <property name="Card Number" value="7" />
      <property name="Icons">
        <s value="power">[Power]</s>
      </property>
    </card>
    <card name="Andrik the Unsmiling" id="8b975ac6-e968-4331-b22f-8cfd9fd6bbb1">
      <property name="Type" value="Character" />
      <property name="Faction" value="House Greyjoy" />
      <property name="Text">Pillage.
<b>Reaction:</b> After Andrik the Unsmiling discards a card using pillage, choose a non-limited location or attachment in the losing opponent's discard pile. Discard 1 copy of that card from play.</property>
      <property name="Traits" value="Ironborn. Raider." />
      <property name="Unique" value="Yes" />
      <property name="Loyal" value="No" />
      <property name="Cost" value="4" />
      <property name="Strength" value="5" />
      <property name="Deck Limit" value="3" />
      <property name="Illustrator" value="Tikos Peter" />
      <property name="Card Number" value="8" />
      <property name="Icons">
        <s value="military">[Military]</s>
      </property>
    </card>
    <card name="Qarl the Maid" id="eaae1577-371f-4d0c-b1de-b9a45abd9f27">
      <property name="Type" value="Character" />
      <property name="Faction" value="House Greyjoy" />
      <property name="Text">
        <b>Reaction:</b> After you win a challenge in which Qarl the Maid is participating, either: stand a <i>Warship</i> location, or stand Asha Greyjoy.</property>
      <property name="Traits" value="Ironborn." />
      <property name="Unique" value="Yes" />
      <property name="Loyal" value="No" />
      <property name="Cost" value="4" />
      <property name="Strength" value="3" />
      <property name="Deck Limit" value="3" />
      <property name="Illustrator" value="Michele Frigo" />
      <property name="Card Number" value="9" />
      <property name="Icons">
        <s value="military">[Military]</s>
        <s value="power">[Power]</s>
      </property>
    </card>
    <card name="Maester Murenmure" id="b6b4e39a-e526-4b9b-ad9d-bf419aad9320">
      <property name="Type" value="Character" />
      <property name="Faction" value="House Greyjoy" />
      <property name="Text">
        <b>Interrupt:</b> When the effects of a triggered location ability would initiate, kneel Maester Murenmure to cancel those effects.</property>
      <property name="Traits" value="Maester." />
      <property name="Unique" value="Yes" />
      <property name="Loyal" value="No" />
      <property name="Cost" value="3" />
      <property name="Strength" value="2" />
      <property name="Deck Limit" value="3" />
      <property name="Illustrator" value="Magali Villeneuve" />
      <property name="Card Number" value="10" />
      <property name="Icons">
        <s value="intrigue">[Intrigue]</s>
        <s value="power">[Power]</s>
      </property>
    </card>
    <card name="Old Grey Gull" id="b95b66e1-2e48-4e73-b210-e5e523558be9">
      <property name="Type" value="Character" />
      <property name="Faction" value="House Greyjoy" />
      <property name="Text">
        <b>Action:</b> Kneel Old Grey Gull to kill another <s value="greyjoy">[House Greyjoy]</s> character you control. Then, you may return that character from your dead pile to your hand.</property>
      <property name="Traits" value="Drowned God. Ironborn." />
      <property name="Unique" value="Yes" />
      <property name="Loyal" value="Yes" />
      <property name="Cost" value="3" />
      <property name="Strength" value="2" />
      <property name="Deck Limit" value="3" />
      <property name="Illustrator" value="Andreia Ugrai" />
      <property name="Card Number" value="11" />
      <property name="Icons">
        <s value="intrigue">[Intrigue]</s>
        <s value="power">[Power]</s>
      </property>
    </card>
    <card name="Priest of Old Wyk" id="f3bd4b67-f1ae-4f67-bab7-35263b05d278">
      <property name="Type" value="Character" />
      <property name="Faction" value="House Greyjoy" />
      <property name="Text">While there is a <i>Drowned God</i> character in your dead pile, Priest of Old Wyk contributes its STR to your total for dominance even while kneeling.</property>
      <property name="Traits" value="Drowned God." />
      <property name="Unique" value="No" />
      <property name="Loyal" value="No" />
      <property name="Cost" value="3" />
      <property name="Strength" value="4" />
      <property name="Deck Limit" value="3" />
      <property name="Illustrator" value="Andreia Ugrai" />
      <property name="Card Number" value="12" />
      <property name="Icons">
        <s value="power">[Power]</s>
      </property>
    </card>
    <card name="Drowned Prophet" id="e608a957-12a2-476e-801b-183b47e0f08a">
      <property name="Type" value="Character" />
      <property name="Faction" value="House Greyjoy" />
      <property name="Text">
        <b>Interrupt:</b> When Drowned Prophet is killed, search the top 5 cards of your deck for a <s value="greyjoy">[House Greyjoy]</s> character and place it in your dead pile. Shuffle your deck.</property>
      <property name="Traits" value="Drowned God." />
      <property name="Unique" value="No" />
      <property name="Loyal" value="No" />
      <property name="Cost" value="2" />
      <property name="Strength" value="2" />
      <property name="Deck Limit" value="3" />
      <property name="Illustrator" value="Andreia Ugrai" />
      <property name="Card Number" value="13" />
      <property name="Icons">
        <s value="power">[Power]</s>
      </property>
    </card>
    <card name="Eager Deckhand" id="d954be86-81cc-4873-84ee-7efa67647cb3">
      <property name="Type" value="Character" />
      <property name="Faction" value="House Greyjoy" />
      <property name="Text">
        <b>Reaction:</b> After a <i>Warship</i> location enters play under your control, put Eager Deckhand into play from your hand.</property>
      <property name="Traits" value="Ally. Raider." />
      <property name="Unique" value="No" />
      <property name="Loyal" value="No" />
      <property name="Cost" value="2" />
      <property name="Strength" value="2" />
      <property name="Deck Limit" value="3" />
      <property name="Illustrator" value="Aleksander Karcz" />
      <property name="Card Number" value="14" />
      <property name="Icons">
        <s value="military">[Military]</s>
      </property>
    </card>
    <card name="Orkmont Reaver" id="6b066d96-b04a-4b2e-ba0e-a3cb1c1607d5">
      <property name="Type" value="Character" />
      <property name="Faction" value="House Greyjoy" />
      <property name="Text">Pillage.
While an opponent has 10 or more cards in his or her discard pile, Orkmont Reaver gains stealth.</property>
      <property name="Traits" value="Ironborn. Raider." />
      <property name="Unique" value="No" />
      <property name="Loyal" value="No" />
      <property name="Cost" value="2" />
      <property name="Strength" value="1" />
      <property name="Deck Limit" value="3" />
      <property name="Illustrator" value="Darek Zabrocki" />
      <property name="Card Number" value="15" />
      <property name="Icons">
        <s value="military">[Military]</s>
        <s value="power">[Power]</s>
      </property>
    </card>
    <card name="Silence" id="a694e078-c1f5-4cf9-9361-0028838c6201">
      <property name="Type" value="Location" />
      <property name="Faction" value="House Greyjoy" />
      <property name="Text">
        <b>Challenges Action:</b> Kneel Silence to put a <i>Warship</i> location into play from your hand. Then, if you control Euron Crow's Eye, stand him.
+2 Initiative.</property>
      <property name="Traits" value="Warship." />
      <property name="Unique" value="Yes" />
      <property name="Loyal" value="Yes" />
      <property name="Cost" value="4" />
      <property name="Deck Limit" value="3" />
      <property name="Illustrator" value="Federico Musetti" />
      <property name="Card Number" value="16" />
    </card>
    <card name="Great Wyk" id="b95d012f-5e27-43ec-b4b8-a4e522a5cfec">
      <property name="Type" value="Location" />
      <property name="Faction" value="House Greyjoy" />
      <property name="Text">
        <b>Reaction:</b> After a character enters play from your dead pile, each opponent chooses and discards 1 card from his or her hand. (Limit once per phase.)</property>
      <property name="Traits" value="Drowned God. Iron Islands." />
      <property name="Unique" value="Yes" />
      <property name="Loyal" value="Yes" />
      <property name="Cost" value="3" />
      <property name="Deck Limit" value="3" />
      <property name="Illustrator" value="Juan Carlos Barquet" />
      <property name="Card Number" value="17" />
    </card>
    <card name="Golden Storm" id="33241281-b3dc-4c9a-aae4-f677300ba053">
      <property name="Type" value="Location" />
      <property name="Faction" value="House Greyjoy" />
      <property name="Text">
        <b>Reaction:</b> After you win a <s value="military">[Military]</s> challenge as the attacking player, kneel Golden Storm to choose and kill a participating character. Then, if you control a participating <i>Raider</i> character, stand Golden Storm.</property>
      <property name="Traits" value="Warship." />
      <property name="Unique" value="Yes" />
      <property name="Loyal" value="No" />
      <property name="Cost" value="2" />
      <property name="Deck Limit" value="3" />
      <property name="Illustrator" value="Alexandre Dainche" />
      <property name="Card Number" value="18" />
    </card>
    <card name="Maiden's Bane" id="2c92f2aa-5901-4e84-90e7-2357c58a84cc">
      <property name="Type" value="Location" />
      <property name="Faction" value="House Greyjoy" />
      <property name="Text">
        <b>Reaction:</b> After you win an unopposed challenge, kneel Maiden's Bane to choose and stand an attacking character. Then, if that character is a <i>Captain</i>, stand Maiden's Bane.</property>
      <property name="Traits" value="Warship." />
      <property name="Unique" value="Yes" />
      <property name="Loyal" value="No" />
      <property name="Cost" value="2" />
      <property name="Deck Limit" value="3" />
      <property name="Illustrator" value="Tomasz Jedruszek" />
      <property name="Card Number" value="19" />
    </card>
    <card name="Scouting Vessel" id="1b21b2b4-950d-40d3-ad53-1419aa81f29d">
      <property name="Type" value="Location" />
      <property name="Faction" value="House Greyjoy" />
      <property name="Text">
        <b>Interrupt:</b> When a character you control discards a card using pillage, kneel and sacrifice Scouting Vessel to discard 3 cards instead.</property>
      <property name="Traits" value="Warship." />
      <property name="Unique" value="No" />
      <property name="Loyal" value="No" />
      <property name="Cost" value="0" />
      <property name="Deck Limit" value="3" />
      <property name="Illustrator" value="Tomasz Jedruszek" />
      <property name="Card Number" value="20" />
    </card>
    <card name="Red Rain" id="e26a3658-5b14-43b4-99e6-d3973eabfafa">
      <property name="Type" value="Attachment" />
      <property name="Faction" value="House Greyjoy" />
      <property name="Text">Unique <s value="greyjoy">[House Greyjoy]</s> character only.
If attached character is The Drumm, he gains stealth.
<b>Reaction:</b> After you win an unopposed challenge in which attached character is attacking, it gains 2 power. (Limit once per phase.)</property>
      <property name="Traits" value="Valyrian Steel. Weapon." />
      <property name="Unique" value="Yes" />
      <property name="Loyal" value="No" />
      <property name="Cost" value="2" />
      <property name="Deck Limit" value="3" />
      <property name="Illustrator" value="Federico Musetti" />
      <property name="Card Number" value="21" />
    </card>
    <card name="Fleet Captain" id="b770fa71-aaed-4807-9fd5-cab7d12eafe9">
      <property name="Type" value="Attachment" />
      <property name="Faction" value="House Greyjoy" />
      <property name="Text">Attached character gains the <i>Captain</i> trait and gets +1 STR. (+3 STR instead if you control 3 or more <i>Warship</i> locations.)</property>
      <property name="Traits" value="Title." />
      <property name="Unique" value="No" />
      <property name="Loyal" value="No" />
      <property name="Cost" value="1" />
      <property name="Deck Limit" value="3" />
      <property name="Illustrator" value="Jason Jenicke" />
      <property name="Card Number" value="22" />
    </card>
    <card name="What Is Dead May Never Die" id="c9c3fa43-44b0-4ada-bd34-05ffbe1ae445">
      <property name="Type" value="Event" />
      <property name="Faction" value="House Greyjoy" />
      <property name="Text">
        <b>Reaction:</b> After you win dominance, choose a <s value="greyjoy">[House Greyjoy]</s> character in your dead pile and put it into play.</property>
      <property name="Traits" value="Drowned God." />
      <property name="Unique" value="No" />
      <property name="Loyal" value="Yes" />
      <property name="Cost" value="3" />
      <property name="Deck Limit" value="3" />
      <property name="Illustrator" value="Axel Sauerwald" />
      <property name="Card Number" value="23" />
    </card>
    <card name="Nighttime Raid" id="275d452e-d43d-4413-bfb7-a97932d8a228">
      <property name="Type" value="Event" />
      <property name="Faction" value="House Greyjoy" />
      <property name="Text">
        <b>Action:</b> Choose up to 3 characters with pillage and/or the <i>Raider</i> trait. Until the end of the phase, each of those characters gains stealth.</property>
      <property name="Unique" value="No" />
      <property name="Loyal" value="No" />
      <property name="Cost" value="1" />
      <property name="Deck Limit" value="3" />
      <property name="Illustrator" value="Aleksander Karcz" />
      <property name="Card Number" value="24" />
    </card>
    <card name="Khorane Sathmantes" id="626510f7-7cfc-46f9-ab74-247ef0476087">
      <property name="Type" value="Character" />
      <property name="Faction" value="House Baratheon" />
      <property name="Text">
        <b>Action:</b> Kneel Khorane Sathmantes and a <i>Warship</i> location to choose and kneel 1 character and 1 location.</property>
      <property name="Traits" value="Captain. Raider. Smuggler." />
      <property name="Unique" value="Yes" />
      <property name="Loyal" value="No" />
      <property name="Cost" value="5" />
      <property name="Strength" value="3" />
      <property name="Deck Limit" value="3" />
      <property name="Illustrator" value="Salvador Trakal" />
      <property name="Card Number" value="25" />
      <property name="Icons">
        <s value="military">[Military]</s>
        <s value="intrigue">[Intrigue]</s>
      </property>
    </card>
    <card name="Fury" id="1c2b37a4-23ad-4692-93e4-56ee872f22df">
      <property name="Type" value="Location" />
      <property name="Faction" value="House Baratheon" />
      <property name="Text">While you control Stannis Baratheon, he gains intimidate.
<b>Reaction:</b> After you win a <s value="power">[Power]</s> challenge, kneel Fury to choose a character or location. Move 1 power from that card to your faction card.</property>
      <property name="Traits" value="Warship." />
      <property name="Unique" value="Yes" />
      <property name="Loyal" value="No" />
      <property name="Cost" value="2" />
      <property name="Deck Limit" value="3" />
      <property name="Illustrator" value="Ignacio Bazán Lazcano" />
      <property name="Card Number" value="26" />
    </card>
    <card name="Gunthor Son of Gurn" id="4cffe212-1568-4742-b25c-cf0c13ff4512">
      <property name="Type" value="Character" />
      <property name="Faction" value="House Lannister" />
      <property name="Text">Ambush (4).
<b>Reaction:</b> After you win a challenge in which Gunthor Son of Gurn is attacking, the losing opponent must choose and discard 1 card from his or her hand.</property>
      <property name="Traits" value="Clansman." />
      <property name="Unique" value="Yes" />
      <property name="Loyal" value="No" />
      <property name="Cost" value="3" />
      <property name="Strength" value="3" />
      <property name="Deck Limit" value="3" />
      <property name="Illustrator" value="Caravan Studio" />
      <property name="Card Number" value="27" />
      <property name="Icons">
        <s value="military">[Military]</s>
        <s value="intrigue">[Intrigue]</s>
      </property>
    </card>
    <card name="My Mind Is My Weapon" id="d497d1a3-6eb8-46ea-9954-f8a1da75da96">
      <property name="Type" value="Event" />
      <property name="Faction" value="House Lannister" />
      <property name="Text">
        <b>Action:</b> During a <s value="military">[Military]</s> challenge, choose a character you control with an <s value="intrigue">[Intrigue]</s> icon and have it participate in the challenge on your side.</property>
      <property name="Unique" value="No" />
      <property name="Loyal" value="No" />
      <property name="Cost" value="1" />
      <property name="Deck Limit" value="3" />
      <property name="Illustrator" value="Aleksander Karcz" />
      <property name="Card Number" value="28" />
    </card>
    <card name="Desert Raider" id="f79eb164-957f-4101-9962-36ed5dfc8631">
      <property name="Type" value="Character" />
      <property name="Faction" value="House Martell" />
      <property name="Text">
        <b>Reaction:</b> After you lose a challenge, put Desert Raider into play from your dead pile and choose a character controlled by the winning opponent. That character gains 1 power. Until the end of the phase, that character loses an <s value="intrigue">[Intrigue]</s> or <s value="power">[Power]</s> icon and Desert Raider gains that icon.</property>
      <property name="Traits" value="Ally. House Dayne. Raider." />
      <property name="Unique" value="No" />
      <property name="Loyal" value="No" />
      <property name="Cost" value="2" />
      <property name="Strength" value="2" />
      <property name="Deck Limit" value="3" />
      <property name="Illustrator" value="Diego Gisbert Llorens" />
      <property name="Card Number" value="29" />
      <property name="Icons">
        <s value="military">[Military]</s>
      </property>
    </card>
    <card name="The Bloodroyal" id="0e7053e9-bd7f-442f-a4c9-471584485951">
      <property name="Type" value="Attachment" />
      <property name="Faction" value="House Martell" />
      <property name="Text">
        <s value="martell">[House Martell]</s> character only.
While you are not the first player, attached character gains stealth and renown.</property>
      <property name="Traits" value="House Yronwood. Title." />
      <property name="Unique" value="Yes" />
      <property name="Loyal" value="No" />
      <property name="Cost" value="1" />
      <property name="Deck Limit" value="3" />
      <property name="Illustrator" value="Michele Frigo" />
      <property name="Card Number" value="30" />
    </card>
    <card name="Vindictive Ranger" id="eeec39e0-683a-4205-bd0f-adb931493bb9">
      <property name="Type" value="Character" />
      <property name="Faction" value="The Night's Watch" />
      <property name="Text">
        <b>Reaction:</b> After you lose a challenge as the defending player, Vindictive Ranger gains stealth and a challenge icon of your choice until the end of the phase.</property>
      <property name="Traits" value="Ranger." />
      <property name="Unique" value="No" />
      <property name="Loyal" value="No" />
      <property name="Cost" value="3" />
      <property name="Strength" value="3" />
      <property name="Deck Limit" value="3" />
      <property name="Illustrator" value="Michele Frigo" />
      <property name="Card Number" value="31" />
      <property name="Icons">
        <s value="military">[Military]</s>
      </property>
    </card>
    <card name="Westwatch-by-the-Bridge" id="2caf43d9-d69d-4616-8444-4b4eb673f19c">
      <property name="Type" value="Location" />
      <property name="Faction" value="The Night's Watch" />
      <property name="Text">
        <b>Action:</b> Kneel Westwatch-by-the-Bridge to choose and stand another <s value="nightswatch">[The Night's Watch]</s> location with printed cost 1 or lower. (Printed cost 4 or lower instead if you control a <i>Ranger</i> character, a <i>Steward</i> character, and a <i>Builder</i> character.)</property>
      <property name="Traits" value="The North." />
      <property name="Unique" value="Yes" />
      <property name="Loyal" value="No" />
      <property name="Cost" value="1" />
      <property name="Deck Limit" value="3" />
      <property name="Illustrator" value="Tomas Honz" />
      <property name="Card Number" value="32" />
    </card>
    <card name="Maester Vyman" id="62897a81-d249-4561-9211-046d4e07547f">
      <property name="Type" value="Character" />
      <property name="Faction" value="House Stark" />
      <property name="Text">
        <b>Reaction:</b> After you win a <s value="military">[Military]</s> or <s value="power">[Power]</s> challenge, kneel Maester Vyman to choose another character that shares a <i>Trait</i> with him. That character gains 1 power.</property>
      <property name="Traits" value="House Tully. Maester." />
      <property name="Unique" value="Yes" />
      <property name="Loyal" value="No" />
      <property name="Cost" value="2" />
      <property name="Strength" value="2" />
      <property name="Deck Limit" value="3" />
      <property name="Illustrator" value="Tiziano Baracchi" />
      <property name="Card Number" value="33" />
      <property name="Icons">
        <s value="power">[Power]</s>
      </property>
    </card>
    <card name="Karhold" id="fbd886e7-41ab-4997-a410-c6572c946117">
      <property name="Type" value="Location" />
      <property name="Faction" value="House Stark" />
      <property name="Text">While a player does not have a <i>Winter</i> plot card revealed, characters and locations he or she controls cannot gain power.</property>
      <property name="Traits" value="The North." />
      <property name="Unique" value="Yes" />
      <property name="Loyal" value="No" />
      <property name="Cost" value="2" />
      <property name="Deck Limit" value="3" />
      <property name="Illustrator" value="Leanna Crossan" />
      <property name="Card Number" value="34" />
    </card>
    <card name="Cohollo" id="448ab3b3-ec73-4721-a365-c05ae3c7ed2d">
      <property name="Type" value="Character" />
      <property name="Faction" value="House Targaryen" />
      <property name="Text">Intimidate.
<b>Action:</b> Kneel Cohollo and discard 1 card from your hand to have him participate in a challenge on your side.</property>
      <property name="Traits" value="Bloodrider. Dothraki." />
      <property name="Unique" value="Yes" />
      <property name="Loyal" value="No" />
      <property name="Cost" value="4" />
      <property name="Strength" value="5" />
      <property name="Deck Limit" value="3" />
      <property name="Illustrator" value="Paolo Puggioni" />
      <property name="Card Number" value="35" />
    </card>
    <card name="&quot;Dance of the Dragons&quot;" id="20e23756-7ee8-4baa-95ba-4e23c2e0c618">
      <property name="Type" value="Event" />
      <property name="Faction" value="House Targaryen" />
      <property name="Text">
        <b>Action:</b> Choose a non-event card with printed cost 3 or lower in your discard pile and return it to your hand.</property>
      <property name="Traits" value="Song." />
      <property name="Unique" value="No" />
      <property name="Loyal" value="No" />
      <property name="Cost" value="1" />
      <property name="Deck Limit" value="3" />
      <property name="Illustrator" value="Tim Durning" />
      <property name="Card Number" value="36" />
    </card>
    <card name="Ser Talbert Serry" id="7f181aaa-b7ae-4199-ba6b-0b79b6c50cd4">
      <property name="Type" value="Character" />
      <property name="Faction" value="House Tyrell" />
      <property name="Text">No attachments except <i>Weapon</i>.
<b>Reaction:</b> After an opponent triggers a location ability, Ser Talbert Serry gets +2 STR until the end of the phase. (Limit 3 times per phase.)</property>
      <property name="Traits" value="Knight." />
      <property name="Unique" value="Yes" />
      <property name="Loyal" value="No" />
      <property name="Cost" value="3" />
      <property name="Strength" value="3" />
      <property name="Deck Limit" value="3" />
      <property name="Illustrator" value="Paolo Puggioni" />
      <property name="Card Number" value="37" />
      <property name="Icons">
        <s value="military">[Military]</s>
        <s value="power">[Power]</s>
      </property>
    </card>
    <card name="The Shield Islands" id="5d4d86ed-a9fe-4723-8f51-0ae9f69ec1e0">
      <property name="Type" value="Location" />
      <property name="Faction" value="House Tyrell" />
      <property name="Text">Increase the number of cards each player draws in the draw phase by 1.</property>
      <property name="Traits" value="The Reach." />
      <property name="Unique" value="Yes" />
      <property name="Loyal" value="No" />
      <property name="Cost" value="2" />
      <property name="Deck Limit" value="3" />
      <property name="Illustrator" value="Leanna Crossan" />
      <property name="Card Number" value="38" />
    </card>
    <card name="Bronze Yohn Royce" id="fe896c9f-1703-4d24-b036-e5fd4cfb55f2">
      <property name="Type" value="Character" />
      <property name="Faction" value="Neutral" />
      <property name="Text">Renown.
<b>Reaction:</b> After you win a challenge in which Bronze Yohn Royce is defending, kneel a neutral location with printed cost 1 or higher to stand him. (Limit twice per phase.)</property>
      <property name="Traits" value="House Arryn. Lord." />
      <property name="Unique" value="Yes" />
      <property name="Loyal" value="No" />
      <property name="Cost" value="6" />
      <property name="Strength" value="5" />
      <property name="Deck Limit" value="3" />
      <property name="Illustrator" value="Even Mehl Amundsen" />
      <property name="Card Number" value="39" />
      <property name="Icons">
        <s value="military">[Military]</s>
        <s value="power">[Power]</s>
      </property>
    </card>
    <card name="Rogue Wildling" id="a4154a33-8446-41e5-a309-ccd8507cfeab">
      <property name="Type" value="Character" />
      <property name="Faction" value="Neutral" />
      <property name="Text">Ambush (5).
<b>Reaction:</b> After Rogue Wildling enters play, choose and stand a <i>Wildling</i> character you control.</property>
      <property name="Traits" value="Raider. Wildling." />
      <property name="Unique" value="No" />
      <property name="Loyal" value="No" />
      <property name="Cost" value="4" />
      <property name="Strength" value="3" />
      <property name="Deck Limit" value="3" />
      <property name="Illustrator" value="Jacob Murray" />
      <property name="Card Number" value="40" />
      <property name="Icons">
        <s value="military">[Military]</s>
        <s value="power">[Power]</s>
      </property>
    </card>
    <card name="Citadel Archivist" id="7388afbd-d68b-48d9-b46e-7699d9e42942">
      <property name="Type" value="Character" />
      <property name="Faction" value="Neutral" />
      <property name="Text">
        <b>Reaction:</b> After Citadel Archivist enters your discard pile, each player shuffles his or her discard pile into his or her deck.</property>
      <property name="Traits" value="Maester." />
      <property name="Unique" value="No" />
      <property name="Loyal" value="No" />
      <property name="Cost" value="2" />
      <property name="Strength" value="1" />
      <property name="Deck Limit" value="3" />
      <property name="Illustrator" value="Aleksander Karcz" />
      <property name="Card Number" value="41" />
      <property name="Icons">
        <s value="intrigue">[Intrigue]</s>
        <s value="power">[Power]</s>
      </property>
    </card>
    <card name="The Starry Sept" id="7eeb6b09-1477-406d-a943-c6c11f915794">
      <property name="Type" value="Location" />
      <property name="Faction" value="Neutral" />
      <property name="Text">
        <b>Action:</b> Move 1 power from The Starry Sept to a character. Until the end of the phase, treat that character as if its printed text box were blank (except for <i>Traits</i>).
<b>Reaction:</b> After you win a <s value="power">[Power]</s> challenge, The Starry Sept gains 1 power.</property>
      <property name="Traits" value="Oldtown. The Seven." />
      <property name="Unique" value="Yes" />
      <property name="Loyal" value="No" />
      <property name="Cost" value="3" />
      <property name="Deck Limit" value="3" />
      <property name="Illustrator" value="Carmen Cornet" />
      <property name="Card Number" value="42" />
    </card>
    <card name="Reckless" id="152ed6d1-efda-4024-9677-42292783201c">
      <property name="Type" value="Attachment" />
      <property name="Faction" value="Neutral" />
      <property name="Text">Terminal.
Attached character must be declared as an attacker or defender in each challenge, if able.</property>
      <property name="Traits" value="Condition." />
      <property name="Unique" value="No" />
      <property name="Loyal" value="No" />
      <property name="Cost" value="0" />
      <property name="Deck Limit" value="3" />
      <property name="Illustrator" value="Ignacio Bazán Lazcano" />
      <property name="Card Number" value="43" />
    </card>
    <card name="When I Woke..." id="c3c1ac32-620b-410c-b468-5d12fdeff03e">
      <property name="Type" value="Event" />
      <property name="Faction" value="Neutral" />
      <property name="Text">
        <b>Reaction:</b> After a player loses a <s value="military">[Military]</s> challenge, that player chooses a participating character and places it on top of its owner's deck. (Max 1 per challenge.)</property>
      <property name="Unique" value="No" />
      <property name="Loyal" value="No" />
      <property name="Cost" value="2" />
      <property name="Deck Limit" value="3" />
      <property name="Illustrator" value="Mike Capprotti" />
      <property name="Card Number" value="44" />
    </card>
    <card name="Sea of Blood" id="f37d6405-6f43-49ce-881c-7a3d212e7cb2">
      <property name="Type" value="Agenda" />
      <property name="Faction" value="Neutral" />
      <property name="Text">During <s value="military">[Military]</s> challenges, reduce the cost of each event you play by 1 for each blood token on Sea of Blood. You cannot play events during <s value="intrigue">[Intrigue]</s> or <s value="power">[Power]</s> challenges.
<b>Reaction:</b> After you win a <s value="military">[Military]</s> challenge by 5 or more STR, kneel your faction card to place a blood token on Sea of Blood. Then, search your deck for an event, reveal it, and add it to your hand. Shuffle your deck.</property>
      <property name="Traits" value="Prophecy." />
      <property name="Unique" value="No" />
      <property name="Loyal" value="No" />
      <property name="Deck Limit" value="1" />
      <property name="Illustrator" value="Tim Durning" />
      <property name="Card Number" value="45" />
    </card>
    <card name="We Take Westeros!" id="7dda0308-c5eb-4c4c-81b1-ad94d05a4cb7" size="HorizontalCards">
      <property name="Type" value="Plot" />
      <property name="Faction" value="House Greyjoy" />
      <property name="Text">
        <b>When Revealed:</b> Choose a location in a discard pile and put it into play under your control.</property>
      <property name="Traits" value="War." />
      <property name="Unique" value="No" />
      <property name="Loyal" value="Yes" />
      <property name="Deck Limit" value="1" />
      <property name="Income" value="5" />
      <property name="Initiative" value="9" />
      <property name="Claim" value="1" />
      <property name="Reserve" value="6" />
      <property name="Illustrator" value="Federico Musetti" />
      <property name="Card Number" value="46" />
    </card>
    <card name="Return to the Fields" id="4ea3af64-24a6-4265-b53d-1bd34cd538e6" size="HorizontalCards">
      <property name="Type" value="Plot" />
      <property name="Faction" value="Neutral" />
      <property name="Text">
        <b>When Revealed:</b> You may sacrifice up to 3 characters. For each character sacrificed this way, draw 1 card and gain 1 gold.</property>
      <property name="Traits" value="Edict." />
      <property name="Unique" value="No" />
      <property name="Loyal" value="No" />
      <property name="Deck Limit" value="2" />
      <property name="Income" value="4" />
      <property name="Initiative" value="6" />
      <property name="Claim" value="1" />
      <property name="Reserve" value="7" />
      <property name="Illustrator" value="Aleksander Karcz" />
      <property name="Card Number" value="47" />
    </card>
    <card name="Heir to the Iron Throne" id="cd4c2a8c-3de6-431e-ae28-771f2e3d3298" size="HorizontalCards">
      <property name="Type" value="Plot" />
      <property name="Faction" value="Neutral" />
      <property name="Text">
        <b>When Revealed:</b> Search the top 10 cards of your deck for a <i>Lord</i> or <i>Lady</i> character and put it into play. Shuffle your deck. Then, sacrifice a <i>Lord</i> or <i>Lady</i> character.</property>
      <property name="Traits" value="Kingdom." />
      <property name="Unique" value="No" />
      <property name="Loyal" value="No" />
      <property name="Deck Limit" value="2" />
      <property name="Income" value="4" />
      <property name="Initiative" value="1" />
      <property name="Claim" value="1" />
      <property name="Reserve" value="6" />
      <property name="Illustrator" value="David Demaret" />
      <property name="Card Number" value="48" />
    </card>
    <card name="Coordinated Attack" id="be430df5-e86a-497c-9d83-ab00b196c91b" size="HorizontalCards">
      <property name="Type" value="Plot" />
      <property name="Faction" value="Neutral" />
      <property name="Text">
        <b>Reaction:</b> After you win a challenge as the attacking player, choose a different challenge type. You may initiate an additional challenge of the chosen type this phase. (Limit once per phase.)</property>
      <property name="Traits" value="War." />
      <property name="Unique" value="No" />
      <property name="Loyal" value="No" />
      <property name="Deck Limit" value="2" />
      <property name="Income" value="3" />
      <property name="Initiative" value="8" />
      <property name="Claim" value="1" />
      <property name="Reserve" value="4" />
      <property name="Illustrator" value="Ignacio Bazán Lazcano" />
      <property name="Card Number" value="49" />
    </card>
    <card name="Stolen Message" id="4b54eff2-d809-4bac-9787-d335294a3e9a" size="HorizontalCards">
      <property name="Type" value="Plot" />
      <property name="Faction" value="Neutral" />
      <property name="Text">Each opponent plays with the top card of his or her deck revealed.
<b>Action:</b> Pay 1 gold to place the top card of an opponent's deck on the bottom of that player's deck. (Limit 3 times per round.)</property>
      <property name="Traits" value="Scheme." />
      <property name="Unique" value="No" />
      <property name="Loyal" value="No" />
      <property name="Deck Limit" value="2" />
      <property name="Income" value="5" />
      <property name="Initiative" value="7" />
      <property name="Claim" value="1" />
      <property name="Reserve" value="6" />
      <property name="Illustrator" value="Carlos Palma Cruchaga" />
      <property name="Card Number" value="50" />
    </card>
    <card name="Secrets of the Conclave" id="718c7cd2-e64b-436a-95fb-0ebacccec22a" size="HorizontalCards">
      <property name="Type" value="Plot" />
      <property name="Faction" value="Neutral" />
      <property name="Text">
        <b>Reaction:</b> After the challenges phase begins, look at the top 5 cards of your deck. Add 1 to your hand, discard 1, and put the others back on top of your deck in any order.</property>
      <property name="Traits" value="Conclave. Kingdom." />
      <property name="Unique" value="No" />
      <property name="Loyal" value="No" />
      <property name="Deck Limit" value="2" />
      <property name="Income" value="4" />
      <property name="Initiative" value="4" />
      <property name="Claim" value="1" />
      <property name="Reserve" value="7" />
      <property name="Illustrator" value="Paolo Puggioni" />
      <property name="Card Number" value="51" />
    </card>
    <card name="Vanquish the Unbelievers" id="e29d5ce8-80cc-46d5-85f7-432ea053830a" size="HorizontalCards">
      <property name="Type" value="Plot" />
      <property name="Faction" value="Neutral" />
      <property name="Text">
        <b>Forced Reaction:</b> After the challenges phase begins, choose a <i>Trait</i>. Kill each character you control that does not have that <i>Trait</i> (cannot be saved).</property>
      <property name="Traits" value="Edict." />
      <property name="Unique" value="No" />
      <property name="Loyal" value="No" />
      <property name="Deck Limit" value="1" />
      <property name="Income" value="5" />
      <property name="Initiative" value="8" />
      <property name="Claim" value="2" />
      <property name="Reserve" value="5" />
      <property name="Illustrator" value="Carlos Palma Cruchaga" />
      <property name="Card Number" value="52" />
    </card>
  </cards>
</set>